seaschedule/__init__.py
seaschedule/__main__.py
seaschedule/config/__init__.py
seaschedule/config/config.toml
seaschedule/config/config_dev.toml
seaschedule/maeu.py
seaschedule/utils/__init__.py
seaschedule/utils/email.py
seaschedule/utils/log.py
seaschedule/utils/sftp.py
seaschedule-0.0.3.dist-info/entry_points.txt
seaschedule-0.0.3.dist-info/WHEEL
seaschedule-0.0.3.dist-info/METADATA
seaschedule-0.0.3.dist-info/RECORD
