Metadata-Version: 2.1
Name: seaschedule
Version: 0.0.3
Summary: Get sea schedules from Maersk and other shipping lines.
Home-page: https://github.com/alexcheng628/seaschedule
License: Proprietary
Author: Alex Cheng
Author-email: alex28.biz@gmail.com
Maintainer: Alex Cheng
Maintainer-email: alex28.biz@gmail.com
Requires-Python: >=3.10,<4.0
Classifier: Development Status :: 3 - Alpha
Classifier: Environment :: Console
Classifier: License :: Other/Proprietary License
Classifier: Programming Language :: Python :: 3
Classifier: Programming Language :: Python :: 3.10
Classifier: Programming Language :: Python :: 3.11
Requires-Dist: pandas (>=1.5.1,<2.0.0)
Requires-Dist: paramiko (>=2.11.0,<3.0.0)
Requires-Dist: requests (>=2.28.1,<3.0.0)
Requires-Dist: tomli (>=2.0.1,<3.0.0)
Project-URL: Documentation, https://github.com/alexcheng628/seaschedule
Project-URL: Repository, https://github.com/alexcheng628/seaschedule
